test_package/__init__.py
test_package/module1.py
text_package-0.1.0.dist-info/METADATA
text_package-0.1.0.dist-info/WHEEL
text_package-0.1.0.dist-info/top_level.txt
text_package-0.1.0.dist-info/RECORD
